nabu/__init__.py
nabu/__main__.py
nabu/menu.py
nabu/nabu.py
nabu/page.py
nabu/serve.py
nabu/watch.py
py_nabu-0.1.4.dist-info/LICENSE
py_nabu-0.1.4.dist-info/METADATA
py_nabu-0.1.4.dist-info/WHEEL
py_nabu-0.1.4.dist-info/entry_points.txt
py_nabu-0.1.4.dist-info/top_level.txt
py_nabu-0.1.4.dist-info/RECORD
